prezo/__init__.py
prezo/app.py
prezo/config.py
prezo/export.py
prezo/images/__init__.py
prezo/images/ascii.py
prezo/images/base.py
prezo/images/chafa.py
prezo/images/iterm.py
prezo/images/kitty.py
prezo/images/overlay.py
prezo/images/processor.py
prezo/images/sixel.py
prezo/parser.py
prezo/screens/__init__.py
prezo/screens/base.py
prezo/screens/blackout.py
prezo/screens/goto.py
prezo/screens/help.py
prezo/screens/overview.py
prezo/screens/search.py
prezo/screens/toc.py
prezo/terminal.py
prezo/themes.py
prezo/widgets/__init__.py
prezo/widgets/image_display.py
prezo/widgets/slide_button.py
prezo/widgets/status_bar.py
prezo-2026.1.1.dist-info/WHEEL
prezo-2026.1.1.dist-info/entry_points.txt
prezo-2026.1.1.dist-info/METADATA
prezo-2026.1.1.dist-info/RECORD
