Metadata-Version: 2.3
Name: prezo
Version: 2026.1.1
Summary: A TUI-based presentation tool for the terminal, built with Textual.
Author: Stefane Fermigier
Author-email: Stefane Fermigier <sf@fermigier.com>
Requires-Dist: textual>=0.89.1
Requires-Dist: textual-image>=0.8.0
Requires-Dist: python-frontmatter>=1.1.0
Requires-Python: >=3.12
